src/__init__.py
src/converter.py
md_to_html-0.7.3.dist-info/LICENSE
md_to_html-0.7.3.dist-info/METADATA
md_to_html-0.7.3.dist-info/WHEEL
md_to_html-0.7.3.dist-info/entry_points.txt
md_to_html-0.7.3.dist-info/top_level.txt
md_to_html-0.7.3.dist-info/RECORD
