Metadata-Version: 2.1
Name: md-to-html
Version: 0.7.3
Summary: Python module for converting Markdown to HTML
Home-page: https://github.com/AumitLeon/markdown_html_converter
Author: Aumit Leon
Author-email: aumitleon@gmail.com
License: UNKNOWN
Keywords: markdown to html
Platform: UNKNOWN
Requires-Python: >=3.5
Requires-Dist: mistune (==0.8.4)
Requires-Dist: beautifulsoup4 (==4.9.3)
Provides-Extra: dev
Requires-Dist: python-semantic-release (==7.7.0) ; extra == 'dev'
Requires-Dist: pytest (==6.2.0) ; extra == 'dev'
Requires-Dist: pre-commit (==2.9.3) ; extra == 'dev'
Requires-Dist: black (==20.8b1) ; extra == 'dev'
Requires-Dist: gitpython (>=3.1) ; extra == 'dev'
Requires-Dist: pyparsing (==2.4.7) ; extra == 'dev'
